README.md
setup.cfg
setup.py
distributionsMOUEZAudacityGitlabAwsMachineLearning/Binomialdistribution.py
distributionsMOUEZAudacityGitlabAwsMachineLearning/Gaussiandistribution.py
distributionsMOUEZAudacityGitlabAwsMachineLearning/Generaldistribution.py
distributionsMOUEZAudacityGitlabAwsMachineLearning/__init__.py
distributionsMOUEZAudacityGitlabAwsMachineLearning.egg-info/PKG-INFO
distributionsMOUEZAudacityGitlabAwsMachineLearning.egg-info/SOURCES.txt
distributionsMOUEZAudacityGitlabAwsMachineLearning.egg-info/dependency_links.txt
distributionsMOUEZAudacityGitlabAwsMachineLearning.egg-info/not-zip-safe
distributionsMOUEZAudacityGitlabAwsMachineLearning.egg-info/top_level.txt